[
  {
    "domain": ".smzdm.com",
    "expirationDate": 1650603874.03572,
    "hostOnly": false,
    "httpOnly": true,
    "name": "__ckguid",
    "path": "/",
    "sameSite": "unspecified",
    "secure": false,
    "session": false,
    "storeId": "0",
    "value": "cFx4ECFpWiCjwXwcJqw1SY3",
    "id": 1
  },
  {
    "domain": ".smzdm.com",
    "expirationDate": 1694585866,
    "hostOnly": false,
    "httpOnly": false,
    "name": "_ga",
    "path": "/",
    "sameSite": "unspecified",
    "secure": false,
    "session": false,
    "storeId": "0",
    "value": "GA1.2.90808546.1619067876",
    "id": 2
  },
  {
    "domain": ".smzdm.com",
    "expirationDate": 1694585866,
    "hostOnly": false,
    "httpOnly": false,
    "name": "_ga_09SRZM2FDD",
    "path": "/",
    "sameSite": "unspecified",
    "secure": false,
    "session": false,
    "storeId": "0",
    "value": "GS1.1.1631513866.37.0.1631513866.0",
    "id": 3
  },
  {
    "domain": ".smzdm.com",
    "expirationDate": 1683870676,
    "hostOnly": false,
    "httpOnly": false,
    "name": "_ga_271744817",
    "path": "/",
    "sameSite": "unspecified",
    "secure": false,
    "session": false,
    "storeId": "0",
    "value": "GS1.1.1620798676.3.0.1620798676.0",
    "id": 4
  },
  {
    "domain": ".smzdm.com",
    "expirationDate": 1631513926,
    "hostOnly": false,
    "httpOnly": false,
    "name": "_gat_UA-27058866-1",
    "path": "/",
    "sameSite": "unspecified",
    "secure": false,
    "session": false,
    "storeId": "0",
    "value": "1",
    "id": 5
  },
  {
    "domain": ".smzdm.com",
    "expirationDate": 1631600266,
    "hostOnly": false,
    "httpOnly": false,
    "name": "_gid",
    "path": "/",
    "sameSite": "unspecified",
    "secure": false,
    "session": false,
    "storeId": "0",
    "value": "GA1.2.419031997.1631513867",
    "id": 6
  },
  {
    "domain": ".smzdm.com",
    "expirationDate": 1633933065,
    "hostOnly": false,
    "httpOnly": false,
    "name": "_zdmA.uid",
    "path": "/",
    "sameSite": "unspecified",
    "secure": false,
    "session": false,
    "storeId": "0",
    "value": "ZDMA.9rilpmU8-.1631513866.2419200",
    "id": 7
  },
  {
    "domain": ".smzdm.com",
    "expirationDate": 1945296893.153492,
    "hostOnly": false,
    "httpOnly": false,
    "name": "device_id",
    "path": "/",
    "sameSite": "unspecified",
    "secure": false,
    "session": false,
    "storeId": "0",
    "value": "37210742901629936894265475938f03cd3db4d69e8bd4c75e38c956f1",
    "id": 8
  },
  {
    "domain": ".smzdm.com",
    "hostOnly": false,
    "httpOnly": false,
    "name": "Hm_lpvt_9b7ac3d38f30fe89ff0b8a0546904e58",
    "path": "/",
    "sameSite": "unspecified",
    "secure": false,
    "session": true,
    "storeId": "0",
    "value": "1631513866",
    "id": 9
  },
  {
    "domain": ".smzdm.com",
    "expirationDate": 1663049865,
    "hostOnly": false,
    "httpOnly": false,
    "name": "Hm_lvt_9b7ac3d38f30fe89ff0b8a0546904e58",
    "path": "/",
    "sameSite": "unspecified",
    "secure": false,
    "session": false,
    "storeId": "0",
    "value": "1629331362,1629334813,1630542037,1631513866",
    "id": 10
  },
  {
    "domain": ".smzdm.com",
    "expirationDate": 1946873864.831952,
    "hostOnly": false,
    "httpOnly": false,
    "name": "homepage_sug",
    "path": "/",
    "sameSite": "unspecified",
    "secure": false,
    "session": false,
    "storeId": "0",
    "value": "c",
    "id": 11
  },
  {
    "domain": ".smzdm.com",
    "expirationDate": 1946873864.832008,
    "hostOnly": false,
    "httpOnly": false,
    "name": "r_sort_type",
    "path": "/",
    "sameSite": "unspecified",
    "secure": false,
    "session": false,
    "storeId": "0",
    "value": "score",
    "id": 12
  },
  {
    "domain": ".smzdm.com",
    "expirationDate": 7938713865,
    "hostOnly": false,
    "httpOnly": false,
    "name": "sensorsdata2015jssdkcross",
    "path": "/",
    "sameSite": "unspecified",
    "secure": false,
    "session": false,
    "storeId": "0",
    "value": "%7B%22distinct_id%22%3A%228999889859%22%2C%22first_id%22%3A%22178f7f72e3111d-087e930f5155cc-3f6b4e04-2073600-178f7f72e32669%22%2C%22props%22%3A%7B%22%24latest_traffic_source_type%22%3A%22%E8%87%AA%E7%84%B6%E6%90%9C%E7%B4%A2%E6%B5%81%E9%87%8F%22%2C%22%24latest_search_keyword%22%3A%22%E6%9C%AA%E5%8F%96%E5%88%B0%E5%80%BC%22%2C%22%24latest_referrer%22%3A%22https%3A%2F%2Fwww.google.com.hk%2F%22%2C%22%24latest_landing_page%22%3A%22https%3A%2F%2Fwww.smzdm.com%2F%22%7D%2C%22%24device_id%22%3A%22178f7f72e3111d-087e930f5155cc-3f6b4e04-2073600-178f7f72e32669%22%7D",
    "id": 13
  },
  {
    "domain": ".smzdm.com",
    "expirationDate": 1632539592.948422,
    "hostOnly": false,
    "httpOnly": true,
    "name": "sess",
    "path": "/",
    "sameSite": "unspecified",
    "secure": false,
    "session": false,
    "storeId": "0",
    "value": "AT-yj3MZizbaXDOkLCmE7BdVOKSQ%2B%2B8142eN3Mh89n0wrzjGQCkx76bktwDpq65j8SpxXXBbZzxdSZ34gFqGfAA5QohObboWZ%2Btjugpbxas8I%2Fs9vfGdIPZ9Tew",
    "id": 14
  },
  {
    "domain": ".smzdm.com",
    "expirationDate": 1942715593.124573,
    "hostOnly": false,
    "httpOnly": false,
    "name": "smzdm_id",
    "path": "/",
    "sameSite": "unspecified",
    "secure": false,
    "session": false,
    "storeId": "0",
    "value": "8999889859",
    "id": 15
  },
  {
    "domain": ".smzdm.com",
    "expirationDate": 64694705064,
    "hostOnly": false,
    "httpOnly": false,
    "name": "smzdm_user_source",
    "path": "/",
    "sameSite": "unspecified",
    "secure": false,
    "session": false,
    "storeId": "0",
    "value": "7D89B72F13C1A00050559BCB8441BC0E",
    "id": 16
  },
  {
    "domain": ".smzdm.com",
    "expirationDate": 1632539592.948467,
    "hostOnly": false,
    "httpOnly": false,
    "name": "user",
    "path": "/",
    "sameSite": "unspecified",
    "secure": false,
    "session": false,
    "storeId": "0",
    "value": "user%3A8999889859%7C8999889859",
    "id": 17
  },
  {
    "domain": ".smzdm.com",
    "expirationDate": 1631773066,
    "hostOnly": false,
    "httpOnly": false,
    "name": "zdm_qd",
    "path": "/",
    "sameSite": "unspecified",
    "secure": false,
    "session": false,
    "storeId": "0",
    "value": "%7B%22referrer%22%3A%22https%3A%2F%2Fwww.google.com.hk%2F%22%7D",
    "id": 18
  },
  {
    "domain": ".www.smzdm.com",
    "expirationDate": 1631516324,
    "hostOnly": false,
    "httpOnly": false,
    "name": "_zdmA.time",
    "path": "/",
    "sameSite": "unspecified",
    "secure": false,
    "session": false,
    "storeId": "0",
    "value": "1631513905756.0.https%3A%2F%2Fwww.smzdm.com%2F",
    "id": 19
  },
  {
    "domain": ".www.smzdm.com",
    "expirationDate": 1631515665,
    "hostOnly": false,
    "httpOnly": false,
    "name": "_zdmA.vid",
    "path": "/",
    "sameSite": "unspecified",
    "secure": false,
    "session": false,
    "storeId": "0",
    "value": "*",
    "id": 20
  },
  {
    "domain": ".www.smzdm.com",
    "expirationDate": 1632118666,
    "hostOnly": false,
    "httpOnly": false,
    "name": "ad_date",
    "path": "/",
    "sameSite": "unspecified",
    "secure": false,
    "session": false,
    "storeId": "0",
    "value": "13",
    "id": 21
  },
  {
    "domain": ".www.smzdm.com",
    "expirationDate": 1632118666,
    "hostOnly": false,
    "httpOnly": false,
    "name": "ad_json_feed",
    "path": "/",
    "sameSite": "unspecified",
    "secure": false,
    "session": false,
    "storeId": "0",
    "value": "%7B%7D",
    "id": 22
  },
  {
    "domain": ".www.smzdm.com",
    "expirationDate": 1632118666,
    "hostOnly": false,
    "httpOnly": false,
    "name": "bannerCounter",
    "path": "/",
    "sameSite": "unspecified",
    "secure": false,
    "session": false,
    "storeId": "0",
    "value": "%5B%7B%22number%22%3A0%2C%22surplus%22%3A1%7D%2C%7B%22number%22%3A0%2C%22surplus%22%3A1%7D%2C%7B%22number%22%3A0%2C%22surplus%22%3A1%7D%2C%7B%22number%22%3A0%2C%22surplus%22%3A1%7D%2C%7B%22number%22%3A0%2C%22surplus%22%3A1%7D%2C%7B%22number%22%3A0%2C%22surplus%22%3A1%7D%5D",
    "id": 23
  },
  {
    "domain": ".www.smzdm.com",
    "expirationDate": 1632118666,
    "hostOnly": false,
    "httpOnly": false,
    "name": "footer_floating_layer",
    "path": "/",
    "sameSite": "unspecified",
    "secure": false,
    "session": false,
    "storeId": "0",
    "value": "0",
    "id": 24
  },
  {
    "domain": "www.smzdm.com",
    "expirationDate": 1650603875.070862,
    "hostOnly": true,
    "httpOnly": true,
    "name": "__jsluid_s",
    "path": "/",
    "sameSite": "no_restriction",
    "secure": true,
    "session": false,
    "storeId": "0",
    "value": "07d875ffa408446543e3fe97f1029380",
    "id": 25
  },
  {
    "domain": "www.smzdm.com",
    "expirationDate": 1694585866,
    "hostOnly": true,
    "httpOnly": false,
    "name": "userId",
    "path": "/",
    "sameSite": "unspecified",
    "secure": false,
    "session": false,
    "storeId": "0",
    "value": "user:8999889859|8999889859",
    "id": 26
  }
]